mlconfig/__init__.py
mlconfig/conf.py
mlconfig/py.typed
mlconfig/torch/__init__.py
mlconfig-0.3.2.dist-info/METADATA
mlconfig-0.3.2.dist-info/WHEEL
mlconfig-0.3.2.dist-info/licenses/LICENSE
mlconfig-0.3.2.dist-info/RECORD
