Metadata-Version: 2.4
Name: mlconfig
Version: 0.3.2
Author-email: narumi <toucans-cutouts0f@icloud.com>
License-File: LICENSE
Requires-Python: >=3.10
Requires-Dist: omegaconf>=2.3.0
